Metadata-Version: 2.1
Name: intelex-service
Version: 1.0.0
Summary: Un servicio para usar las api de IntelligenceX
Home-page: UNKNOWN
Author: Fermin
License: MIT
Keywords: python,package,distribution
Platform: UNKNOWN
License-File: LICENSE
